pparser/__init__.py
pparser/__main__.py
pparser/art.py
pparser/commands.py
pparser/exceptions.py
pparser/main.py
pparser/parser.py
pparser/payloads.py
pparser/sketch.py
pparser/utils.py
pparser/alphabets/ascii.json
pparser/alphabets/russian.json
pparser-2.0.2.dist-info/LICENSE
pparser-2.0.2.dist-info/METADATA
pparser-2.0.2.dist-info/WHEEL
pparser-2.0.2.dist-info/entry_points.txt
pparser-2.0.2.dist-info/top_level.txt
pparser-2.0.2.dist-info/RECORD
