Metadata-Version: 2.1
Name: pparser
Version: 2.0.2
Summary: Parser from Ducky Script to Ardunio
Author-email: Yaroslav Kikel <yaroslav.kikel.06@inbox.ru>
License: GPL-3.0-or-later
Project-URL: Documentation, https://pparser.readthedocs.io
Project-URL: Homepage, https://github.com/YariKartoshe4ka/PotatoParser
Project-URL: Source, https://github.com/YariKartoshe4ka/PotatoParser
Project-URL: Tracker, https://github.com/YariKartoshe4ka/PotatoParser/issues
Keywords: parser,ducky,arduino,badusb
Classifier: Development Status :: 5 - Production/Stable
Classifier: License :: OSI Approved :: GNU General Public License v3 or later (GPLv3+)
Classifier: Operating System :: OS Independent
Classifier: Programming Language :: Python
Classifier: Programming Language :: Python :: 3
Classifier: Programming Language :: Python :: 3 :: Only
Classifier: Programming Language :: Python :: 3.7
Classifier: Programming Language :: Python :: 3.8
Classifier: Programming Language :: Python :: 3.9
Classifier: Programming Language :: Python :: 3.10
Classifier: Programming Language :: Python :: Implementation :: CPython
Classifier: Topic :: Software Development :: Code Generators
Classifier: Environment :: Console
License-File: LICENSE
Requires-Dist: colorama (>=0.4.3)
Requires-Dist: requests (>=2.24.0)
Requires-Dist: packaging (>=20.4)
Provides-Extra: docs
Requires-Dist: sphinx (>=4) ; extra == 'docs'
Requires-Dist: sphinx-rtd-theme (>=1.0.0) ; extra == 'docs'
Requires-Dist: sphinxcontrib-video ; extra == 'docs'
